pubnub/__init__.py
pubnub/builders.py
pubnub/callbacks.py
pubnub/crypto.py
pubnub/crypto_core.py
pubnub/crypto_legacy.py
pubnub/dtos.py
pubnub/enums.py
pubnub/errors.py
pubnub/exceptions.py
pubnub/managers.py
pubnub/pnconfiguration.py
pubnub/pubnub.py
pubnub/pubnub_asyncio.py
pubnub/pubnub_core.py
pubnub/pubnub_tornado.py
pubnub/pubnub_twisted.py
pubnub/structures.py
pubnub/utils.py
pubnub/workers.py
pubnub/endpoints/__init__.py
pubnub/endpoints/endpoint.py
pubnub/endpoints/history.py
pubnub/endpoints/time.py
pubnub/endpoints/access/__init__.py
pubnub/endpoints/access/audit.py
pubnub/endpoints/access/grant.py
pubnub/endpoints/access/revoke.py
pubnub/endpoints/channel_groups/__init__.py
pubnub/endpoints/channel_groups/add_channel_to_channel_group.py
pubnub/endpoints/channel_groups/list_channels_in_channel_group.py
pubnub/endpoints/channel_groups/remove_channel_from_channel_group.py
pubnub/endpoints/channel_groups/remove_channel_group.py
pubnub/endpoints/presence/__init__.py
pubnub/endpoints/presence/get_state.py
pubnub/endpoints/presence/heartbeat.py
pubnub/endpoints/presence/here_now.py
pubnub/endpoints/presence/leave.py
pubnub/endpoints/presence/set_state.py
pubnub/endpoints/presence/where_now.py
pubnub/endpoints/pubsub/__init__.py
pubnub/endpoints/pubsub/publish.py
pubnub/endpoints/pubsub/subscribe.py
pubnub/endpoints/push/__init__.py
pubnub/endpoints/push/add_channels_to_push.py
pubnub/endpoints/push/list_push_provisions.py
pubnub/endpoints/push/remove_channels_from_push.py
pubnub/endpoints/push/remove_device.py
pubnub/models/__init__.py
pubnub/models/subscription_item.py
pubnub/models/consumer/__init__.py
pubnub/models/consumer/access_manager.py
pubnub/models/consumer/channel_group.py
pubnub/models/consumer/common.py
pubnub/models/consumer/history.py
pubnub/models/consumer/pn_error_data.py
pubnub/models/consumer/presence.py
pubnub/models/consumer/pubsub.py
pubnub/models/consumer/push.py
pubnub-4.0.13.dist-info/DESCRIPTION.rst
pubnub-4.0.13.dist-info/METADATA
pubnub-4.0.13.dist-info/RECORD
pubnub-4.0.13.dist-info/WHEEL
pubnub-4.0.13.dist-info/metadata.json
pubnub-4.0.13.dist-info/top_level.txt
