Metadata-Version: 1.1
Name: pubnub
Version: 4.0.13
Summary: PubNub Real-time push service in the cloud
Home-page: http://pubnub.com
Author: PubNub
Author-email: support@pubnub.com
License: MIT
Platform: UNKNOWN
Classifier: Development Status :: 5 - Production/Stable
Classifier: Intended Audience :: Developers
Classifier: Programming Language :: Python
Classifier: License :: OSI Approved :: MIT License
Classifier: Operating System :: OS Independent
Classifier: Topic :: Internet :: WWW/HTTP
Classifier: Topic :: Software Development :: Libraries :: Python Modules
